collaborative_gym/__init__.py
collaborative_gym/command.py
collaborative_gym/core.py
collaborative_gym/runner.py
collaborative_gym/server.py
collaborative_gym/spaces.py
collaborative_gym/envs/__init__.py
collaborative_gym/envs/config.py
collaborative_gym/envs/lesson_planning.py
collaborative_gym/envs/literature_survey.py
collaborative_gym/envs/registry.py
collaborative_gym/envs/tabular_analysis.py
collaborative_gym/envs/travel_planning.py
collaborative_gym/envs/travel_planner/LICENSE
collaborative_gym/envs/travel_planner/__init__.py
collaborative_gym/envs/travel_planner/evaluation/__init__.py
collaborative_gym/envs/travel_planner/evaluation/commonsense_constraint.py
collaborative_gym/envs/travel_planner/evaluation/hard_constraint.py
collaborative_gym/envs/travel_planner/tools/__init__.py
collaborative_gym/envs/travel_planner/tools/accommodations/__init__.py
collaborative_gym/envs/travel_planner/tools/accommodations/apis.py
collaborative_gym/envs/travel_planner/tools/attractions/apis.py
collaborative_gym/envs/travel_planner/tools/flights/__init__.py
collaborative_gym/envs/travel_planner/tools/flights/apis.py
collaborative_gym/envs/travel_planner/tools/googleDistanceMatrix/apis.py
collaborative_gym/envs/travel_planner/tools/restaurants/__init__.py
collaborative_gym/envs/travel_planner/tools/restaurants/apis.py
collaborative_gym/envs/travel_planner/utils/func.py
collaborative_gym/eval/controlled_autonomy.py
collaborative_gym/eval/initiative_analysis.py
collaborative_gym/nodes/__init__.py
collaborative_gym/nodes/agent_interface.py
collaborative_gym/nodes/base_node.py
collaborative_gym/nodes/cmd_user.py
collaborative_gym/nodes/commons.py
collaborative_gym/nodes/gui_user.py
collaborative_gym/nodes/simulated_user.py
collaborative_gym/nodes/task_env.py
collaborative_gym/utils/__init__.py
collaborative_gym/utils/business_search.py
collaborative_gym/utils/code_executor.py
collaborative_gym/utils/context_processing.py
collaborative_gym/utils/dict.py
collaborative_gym-0.1.2.dist-info/licenses/LICENSE
collaborative_gym-0.1.2.dist-info/METADATA
collaborative_gym-0.1.2.dist-info/WHEEL
collaborative_gym-0.1.2.dist-info/entry_points.txt
collaborative_gym-0.1.2.dist-info/top_level.txt
collaborative_gym-0.1.2.dist-info/RECORD
